auther/__main__.py
auther/cli.py
auther/exceptions.py
auther/providers/BaseProvider.py
auther/providers/__init__.py
auther/providers/adfs.py
auther/providers/azuread.py
auther/providers/helpers/__init__.py
auther/providers/helpers/azuread.py
auther-0.0.6.dist-info/LICENSE
auther-0.0.6.dist-info/METADATA
auther-0.0.6.dist-info/WHEEL
auther-0.0.6.dist-info/entry_points.txt
auther-0.0.6.dist-info/top_level.txt
auther-0.0.6.dist-info/RECORD
