Metadata-Version: 2.1
Name: auther
Version: 0.0.6
Summary: Command line tool for AWS CLI authentication
Home-page: https://github.com/trewq34/auther
Author: Kamran Ali
Author-email: auther@trewq34.com
Project-URL: Bug Tracker, https://github.com/trewq34/auther/issues
Classifier: Programming Language :: Python :: 3
Classifier: License :: OSI Approved :: MIT License
Classifier: Operating System :: OS Independent
License-File: LICENSE
Requires-Dist: typer
Requires-Dist: requests
Requires-Dist: boto3
Requires-Dist: bs4
Requires-Dist: pyppeteer
Requires-Dist: asyncio
